[{"root":"ha!","esp":"ha!","jp":"［間］はっ！","cn":"啊！（对突然发现的好事或坏事表示意外"},{"root":"ho!","esp":"ho!","jp":"［間］おお！","cn":"嗬！啊！"},{"root":"ajn","esp":"ajn","jp":"［副］～であっても（無差別を示す）","cn":"无论"},{"root":"almenaŭ","esp":"almenaŭ","jp":"［副］少なくとも","cn":"至少"},{"root":"ambaŭ","esp":"ambaŭ","jp":"［形］両方の","cn":"两者的"},{"root":"ankaŭ","esp":"ankaŭ","jp":"［副］～もまた","cn":"也"},{"root":"ankoraŭ","esp":"ankoraŭ","jp":"［副］まだ","cn":"还"},{"root":"apenaŭ","esp":"apenaŭ","jp":"［副］やっと","cn":"几乎不"},{"root":"aŭ","esp":"aŭ","jp":"［接］または","cn":"或者"},{"root":"baldaŭ","esp":"baldaŭ","jp":"［副］まもなく","cn":"不久"},{"root":"ĉar","esp":"ĉar","jp":"［接］～だから","cn":"因为"},{"root":"ĉu","esp":"ĉu","jp":"［副］～か（疑問文を作る）","cn":"（疑问副词）吗"},{"root":"do","esp":"do","jp":"［接］だから","cn":"（接）所以"},{"root":"eĉ","esp":"eĉ","jp":"［副］さえ","cn":"甚至"},{"root":"for","esp":"for","jp":"［副］遠くへ","cn":"往远处"},{"root":"ĝi","esp":"ĝi","jp":"［代］それ（人以外の事物・生物）","cn":"它"},{"root":"hieraŭ","esp":"hieraŭ","jp":"［副］きのう","cn":"昨天"},{"root":"hodiaŭ","esp":"hodiaŭ","jp":"［副］きょう","cn":"今天"},{"root":"ili","esp":"ili","jp":"［代］（三人称複数）彼ら","cn":"他（她、它）们"},{"root":"ja","esp":"ja","jp":"［副］実に","cn":"确实"},{"root":"jam","esp":"jam","jp":"［副］既に","cn":"已经"},{"root":"jen","esp":"jen","jp":"［副］（相手の注意を引いて）そらここに","cn":"看"},{"root":"jes","esp":"jes","jp":"［副］はい","cn":"是"},{"root":"ĵus","esp":"ĵus","jp":"［副］たった今","cn":"刚才"},{"root":"kaj","esp":"kaj","jp":"［接］～と～","cn":"和"},{"root":"ke","esp":"ke","jp":"［接］～ということ","cn":"（连）…这个事实"},{"root":"kvankam","esp":"kvankam","jp":"［接］（～だ）けれども","cn":"虽然"},{"root":"kvazaŭ","esp":"kvazaŭ","jp":"［副］まるで～のように","cn":"好像"},{"root":"li","esp":"li","jp":"［代］彼","cn":"他"},{"root":"mem","esp":"mem","jp":"［副］～自身","cn":"本人"},{"root":"mi","esp":"mi","jp":"［代］私","cn":"我"},{"root":"morgaŭ","esp":"morgaŭ","jp":"［副］明日","cn":"明天"},{"root":"ne","esp":"ne","jp":"［副］（～で）ない","cn":"不"},{"root":"nek","esp":"nek","jp":"［接］～もまた～ない","cn":"也不"},{"root":"ni","esp":"ni","jp":"［代］私たち","cn":"我们"},{"root":"nu","esp":"nu","jp":"［間］さて！","cn":"那么"},{"root":"nun","esp":"nun","jp":"［副］いま（今）","cn":"现在"},{"root":"nur","esp":"nur","jp":"［副］ただ～だけ","cn":"仅"},{"root":"ol","esp":"ol","jp":"［接］～よりも","cn":"比"},{"root":"oni","esp":"oni","jp":"［代］（一般・不特定の）人","cn":"人"},{"root":"plej","esp":"plej","jp":"［副］もっとも","cn":"最"},{"root":"pli","esp":"pli","jp":"［副］より","cn":"更加"},{"root":"plu","esp":"plu","jp":"［副］さらに","cn":"继续"},{"root":"preskaŭ","esp":"preskaŭ","jp":"［副］ほとんど～","cn":"几乎"},{"root":"se","esp":"se","jp":"［接］もし～なら","cn":"如果"},{"root":"sed","esp":"sed","jp":"［接］しかし","cn":"但是"},{"root":"si","esp":"si","jp":"［代］自分","cn":"［代］自己（第三人称反身）"},{"root":"ŝi","esp":"ŝi","jp":"［代］彼女","cn":"她"},{"root":"tamen","esp":"tamen","jp":"［副］とはいえ","cn":"可是"},{"root":"tre","esp":"tre","jp":"［副］とても","cn":"很"},{"root":"tro","esp":"tro","jp":"［副］あまりに～すぎる","cn":"太"},{"root":"tuj","esp":"tuj","jp":"［副］すぐ","cn":"立刻"},{"root":"vi","esp":"vi","jp":"［代］あなた","cn":"你"},{"root":"alia","esp":"alia","jp":"ほかの","cn":"别的"},{"root":"ha","esp":"ha","jp":"［間］あっ！（驚き）","cn":"哈！啊！"},{"root":"ho","esp":"ho","jp":"［間］（驚き・強い感情）おお！","cn":"噢！哇！"},{"root":"adiaŭ","esp":"adiaŭ","jp":"［間］さようなら","cn":"再见"},{"root":"ve!","esp":"ve!","jp":"［間］ああ！","cn":"唉！咳！哎呀！"},{"root":"he!","esp":"he!","jp":"［間］おい！（ねえ！）","cn":"喂！"},{"root":"minus","esp":"minus","jp":"［接］マイナス（引き算・負数）","cn":"减号"},{"root":"plus","esp":"plus","jp":"［接］プラス（足し算・正数）","cn":"加"},{"root":"bis","esp":"bis","jp":"［間］アンコール！","cn":"[叹] 再来一次（喝彩）"},{"root":"fi","esp":"fi","jp":"［間］チェッ！","cn":"呸！"},{"root":"he","esp":"he","jp":"［間］おい！","cn":"嘿！喂！"},{"root":"ve","esp":"ve","jp":"［間］ああ！（悲哀・嘆き・失望）","cn":"哎呀！呜呼！"},{"root":"fi!","esp":"fi!","jp":"［間］チェッ！（ふん！）","cn":"呸！（表示嫌恶"}]
